[{"timestamp":"2023-09-06T00:09:14.769Z","count":0,"uniques":0},{"timestamp":"2023-09-07T00:08:57.831Z","count":0,"uniques":0},{"timestamp":"2023-09-08T00:08:59.800Z","count":0,"uniques":0},{"timestamp":"2023-09-09T00:08:59.298Z","count":0,"uniques":0},{"timestamp":"2023-09-10T00:09:45.005Z","count":0,"uniques":0},{"timestamp":"2023-09-11T00:09:14.634Z","count":0,"uniques":0},{"timestamp":"2023-09-12T00:09:07.199Z","count":0,"uniques":0},{"timestamp":"2023-09-13T00:09:09.672Z","count":0,"uniques":0}]
