[{"timestamp":"2022-08-24T00:11:21.075Z","count":0,"uniques":0},{"timestamp":"2022-08-25T00:00:00.000Z","count":1,"uniques":1},{"timestamp":"2022-08-26T00:11:23.652Z","count":0,"uniques":0},{"timestamp":"2022-08-27T00:10:52.318Z","count":0,"uniques":0},{"timestamp":"2022-08-28T00:14:27.826Z","count":0,"uniques":0},{"timestamp":"2022-08-29T00:11:23.764Z","count":0,"uniques":0},{"timestamp":"2022-08-30T00:13:02.416Z","count":0,"uniques":0},{"timestamp":"2022-08-31T00:12:57.242Z","count":0,"uniques":0}]
