[{"timestamp":"2024-12-02T00:14:16.005Z","count":0,"uniques":0},{"timestamp":"2024-12-03T00:14:54.154Z","count":0,"uniques":0},{"timestamp":"2024-12-04T00:13:58.843Z","count":0,"uniques":0},{"timestamp":"2024-12-05T00:13:55.894Z","count":0,"uniques":0},{"timestamp":"2024-12-06T00:13:58.595Z","count":0,"uniques":0},{"timestamp":"2024-12-07T00:13:30.696Z","count":0,"uniques":0},{"timestamp":"2024-12-08T00:14:54.790Z","count":0,"uniques":0},{"timestamp":"2024-12-09T00:14:23.375Z","count":0,"uniques":0}]
